src/102003701.py
Topsis_102003701_Akshit_0.2-0.0.2.dist-info/LICENSE.txt
Topsis_102003701_Akshit_0.2-0.0.2.dist-info/METADATA
Topsis_102003701_Akshit_0.2-0.0.2.dist-info/WHEEL
Topsis_102003701_Akshit_0.2-0.0.2.dist-info/entry_points.txt
Topsis_102003701_Akshit_0.2-0.0.2.dist-info/top_level.txt
Topsis_102003701_Akshit_0.2-0.0.2.dist-info/RECORD
