Metadata-Version: 2.1
Name: Topsis-102003701-Akshit-0.2
Version: 0.0.2
Summary: A Python package implementing TOPSIS technique.
Author: Akshit Miglani
Author-email: amiglani_be20@thapar.edu
License: MIT
Classifier: License :: OSI Approved :: MIT License
Classifier: Programming Language :: Python :: 3
Classifier: Programming Language :: Python :: 3.4
Classifier: Programming Language :: Python :: 3.5
Classifier: Programming Language :: Python :: 3.6
Classifier: Programming Language :: Python :: 3.7
License-File: LICENSE.txt
Requires-Dist: numpy
Requires-Dist: pandas
